Workbook

Sheet Quarterly Budget Logframe
A1: MooMe — IoT-AI Livestock Intelligence Platform
A2: Quarterly Budget Breakdown — Solution Design, Development & Promotion | 3-Year Logframe
A3: =CONCATENATE("Grand Total: USD ",TEXT(R28,"$#,##0")," over 3 Years")
A5: Category | B5: Activity / Deliverable | C5: Year 1 | H5: Year 2 | M5: Year 3 | R5: Total
C6: Q1 | D6: Q2 | E6: Q3 | F6: Q4 | G6: Y1 Total | H6: Q1 | I6: Q2 | J6: Q3 | K6: Q4 | L6: Y2 Total | M6: Q1 | N6: Q2 | O6: Q3 | P6: Q4 | Q6: Y3 Total
A7: SOLUTION DESIGN | B7: System Architecture & Requirements | C7: 8000 | D7: 5000 | E7: 0 | F7: 0 | G7: =SUM(C7:F7) | H7: 4000 | I7: 2000 | J7: 0 | K7: 0 | L7: =SUM(H7:K7) | M7: 3000 | N7: 0 | O7: 0 | P7: 0 | Q7: =SUM(M7:P7) | R7: =G7+L7+Q7
B8: IoT Sensor Design & GHG Sensor Spec | C8: 6000 | D8: 5000 | E8: 2000 | F8: 0 | G8: =SUM(C8:F8) | H8: 3000 | I8: 3000 | J8: 2000 | K8: 0 | L8: =SUM(H8:K8) | M8: 3000 | N8: 2000 | O8: 0 | P8: 0 | Q8: =SUM(M8:P8) | R8: =G8+L8+Q8
B9: AI/ML Model Design (Disease, GHG, Yield) | C9: 5000 | D9: 5000 | E9: 3000 | F9: 2000 | G9: =SUM(C9:F9) | H9: 4000 | I9: 4000 | J9: 3000 | K9: 2000 | L9: =SUM(H9:K9) | M9: 3000 | N9: 3000 | O9: 3000 | P9: 2000 | Q9: =SUM(M9:P9) | R9: =G9+L9+Q9
B10: GHG / Biogas Monitoring System Design | C10: 4000 | D10: 4000 | E10: 2000 | F10: 0 | G10: =SUM(C10:F10) | H10: 3000 | I10: 3000 | J10: 2000 | K10: 2000 | L10: =SUM(H10:K10) | M10: 3000 | N10: 3000 | O10: 2000 | P10: 2000 | Q10: =SUM(M10:P10) | R10: =G10+L10+Q10
B11: Dashboard & Mobile App UX/UI Design | C11: 3000 | D11: 3000 | E11: 2000 | F11: 1000 | G11: =SUM(C11:F11) | H11: 2000 | I11: 2000 | J11: 2000 | K11: 1000 | L11: =SUM(H11:K11) | M11: 2000 | N11: 2000 | O11: 1000 | P11: 1000 | Q11: =SUM(M11:P11) | R11: =G11+L11+Q11
B12: Design Subtotal | C12: =SUM(C7:C11) | D12: =SUM(D7:D11) | E12: =SUM(E7:E11) | F12: =SUM(F7:F11) | G12: =SUM(G7:G11) | H12: =SUM(H7:H11) | I12: =SUM(I7:I11) | J12: =SUM(J7:J11) | ... Q12: =SUM(Q7:Q11) | R12: =G12+L12+Q12
A13: SOLUTION DEVELOPMENT | B13: IoT Hardware Procurement & Assembly | C13: 3000 | D13: 10000 | E13: 8000 | F13: 4000 | G13: =SUM(C13:F13) | H13: 6000 | I13: 8000 | J13: 7000 | K13: 5000 | L13: =SUM(H13:K13) | M13: 8000 | N13: 10000 | O13: 8000 | P13: 6000 | Q13: =SUM(M13:P13) | R13: =G13+L13+Q13
B14: Embedded Software & Firmware Dev | C14: 2000 | D14: 4000 | E14: 5000 | F14: 4000 | G14: =SUM(C14:F14) | H14: 4000 | I14: 5000 | J14: 5000 | K14: 4000 | L14: =SUM(H14:K14) | M14: 5000 | N14: 6000 | O14: 6000 | P14: 5000 | Q14: =SUM(M14:P14) | R14: =G14+L14+Q14
B15: AI Model Training & Deployment | C15: 0 | D15: 3000 | E15: 5000 | F15: 5000 | G15: =SUM(C15:F15) | H15: 5000 | I15: 6000 | J15: 6000 | K15: 5000 | L15: =SUM(H15:K15) | M15: 7000 | N15: 7000 | O15: 7000 | P15: 6000 | Q15: =SUM(M15:P15) | R15: =G15+L15+Q15
B16: Web Dashboard & Mobile App Dev | C16: 0 | D16: 3000 | E16: 5000 | F16: 5000 | G16: =SUM(C16:F16) | H16: 5000 | I16: 6000 | J16: 5000 | K16: 5000 | L16: =SUM(H16:K16) | M16: 6000 | N16: 7000 | O16: 6000 | P16: 6000 | Q16: =SUM(M16:P16) | R16: =G16+L16+Q16
B17: GHG Monitoring, Biogas & NDC Integration | C17: 1000 | D17: 3000 | E17: 4000 | F17: 4000 | G17: =SUM(C17:F17) | H17: 4000 | I17: 5000 | J17: 5000 | K17: 4000 | L17: =SUM(H17:K17) | M17: 5000 | N17: 6000 | O17: 6000 | P17: 5000 | Q17: =SUM(M17:P17) | R17: =G17+L17+Q17
B18: Cloud Infrastructure, Database & APIs | C18: 2000 | D18: 3000 | E18: 3000 | F18: 4479 | G18: =SUM(C18:F18) | H18: 4000 | I18: 4000 | J18: 4000 | K18: 4575 | L18: =SUM(H18:K18) | M18: 5000 | N18: 5000 | O18: 5000 | P18: 5233 | Q18: =SUM(M18:P18) | R18: =G18+L18+Q18
B19: Testing, QA & Pilot Deployment | C19: 0 | D19: 0 | E19: 5000 | F19: 7000 | G19: =SUM(C19:F19) | H19: 4000 | I19: 5000 | J19: 5000 | K19: 5000 | L19: =SUM(H19:K19) | M19: 5000 | N19: 6000 | O19: 6000 | P19: 6000 | Q19: =SUM(M19:P19) | R19: =G19+L19+Q19
B20: Development Subtotal | C20: =SUM(C13:C19) | D20: =SUM(D13:D19) | E20: =SUM(E13:E19) | F20: =SUM(F13:F19) | G20: =SUM(G13:G19) | H20: =SUM(H13:H19) | I20: =SUM(I13:I19) | J20: =SUM(J13:J19) | ... Q20: =SUM(Q13:Q19) | R20: =G20+L20+Q20
A21: SOLUTION PROMOTION | B21: Farmer Training & Capacity Building | C21: 0 | D21: 0 | E21: 3000 | F21: 3000 | G21: =SUM(C21:F21) | H21: 3000 | I21: 3000 | J21: 3000 | K21: 2000 | L21: =SUM(H21:K21) | M21: 3000 | N21: 3000 | O21: 2000 | P21: 2000 | Q21: =SUM(M21:P21) | R21: =G21+L21+Q21
B22: Stakeholder Engagement & Live Demos | C22: 1000 | D22: 2000 | E22: 2000 | F22: 1000 | G22: =SUM(C22:F22) | H22: 2000 | I22: 2000 | J22: 3000 | K22: 2000 | L22: =SUM(H22:K22) | M22: 2000 | N22: 2000 | O22: 2000 | P22: 2000 | Q22: =SUM(M22:P22) | R22: =G22+L22+Q22
B23: NDC / GHG Impact Reports & Publications | C23: 0 | D23: 0 | E23: 2000 | F23: 3000 | G23: =SUM(C23:F23) | H23: 2000 | I23: 2000 | J23: 3000 | K23: 2000 | L23: =SUM(H23:K23) | M23: 3000 | N23: 3000 | O23: 2000 | P23: 2000 | Q23: =SUM(M23:P23) | R23: =G23+L23+Q23
B24: Marketing, Branding & Conferences | C24: 2000 | D24: 2000 | E24: 3000 | F24: 2000 | G24: =SUM(C24:F24) | H24: 3000 | I24: 3000 | J24: 2000 | K24: 3000 | L24: =SUM(H24:K24) | M24: 3000 | N24: 3000 | O24: 3000 | P24: 3000 | Q24: =SUM(M24:P24) | R24: =G24+L24+Q24
B25: Partnership Dev & Green Fund Applications | C25: 2000 | D25: 3000 | E25: 3000 | F25: 4000 | G25: =SUM(C25:F25) | H25: 3000 | I25: 3000 | J25: 4000 | K25: 4000 | L25: =SUM(H25:K25) | M25: 3000 | N25: 4000 | O25: 4000 | P25: 4000 | Q25: =SUM(M25:P25) | R25: =G25+L25+Q25
B26: Monitoring & Evaluation (M&E) | C26: 1000 | D26: 0 | E26: 1000 | F26: 3000 | G26: =SUM(C26:F26) | H26: 1000 | I26: 2000 | J26: 2000 | K26: 3000 | L26: =SUM(H26:K26) | M26: 1000 | N26: 3000 | O26: 4000 | P26: 2000 | Q26: =SUM(M26:P26) | R26: =G26+L26+Q26
B27: Promotion Subtotal | C27: =SUM(C21:C26) | D27: =SUM(D21:D26) | E27: =SUM(E21:E26) | F27: =SUM(F21:F26) | G27: =SUM(G21:G26) | H27: =SUM(H21:H26) | I27: =SUM(I21:I26) | J27: =SUM(J21:J26) | ... Q27: =SUM(Q21:Q26) | R27: =G27+L27+Q27
A28: QUARTERLY TOTALS | C28: =C12+C20+C27 | D28: =D12+D20+D27 | E28: =E12+E20+E27 | F28: =F12+F20+F27 | G28: =G12+G20+G27 | H28: =H12+H20+H27 | I28: =I12+I20+I27 | J28: =J12+J20+J27 | ... R28: =R12+R20+R27
A30: ANNUAL TOTALS | G30: =G28 | L30: =L28 | Q30: =Q28 | R30: =R28

Sheet Hardware Budget
A1: MooMe — Hardware Component Budget (Prototype)
A2: Prices in USD — Included in the $723,287 Global Budget
A3: # | B3: Component | C3: Qty | D3: Unit Price (USD) | E3: Total (USD)
A4: 1 | B4: Raspberry Pi 4/5 | C4: 1 | D4: 102 | E4: =C4*D4
A5: 2 | B5: MicroSD Card (64GB) | C5: 1 | D5: 13 | E5: =C5*D5
A6: 3 | B6: Power Supply | C6: 1 | D6: 9 | E6: =C6*D6
A7: 4 | B7: Non-contact Temp Sensor (IR) | C7: 12 | D7: 17 | E7: =C7*D7
A8: 5 | B8: DHT22 Sensor | C8: 2 | D8: 7 | E8: =C8*D8
A9: 6 | B9: Air Quality Sensor (MQ-135) | C9: 1 | D9: 13 | E9: =C9*D9
A10: 7 | B10: Oxygen Sensor | C10: 1 | D10: 21 | E10: =C10*D10
A11: 8 | B11: RFID Reader Module | C11: 1 | D11: 15 | E11: =C11*D11
A12: 9 | B12: RFID Tags | C12: 12 | D12: 2 | E12: =C12*D12
A13: 10 | B13: Water Flow Sensor | C13: 12 | D13: 9 | E13: =C13*D13
A14: 11 | B14: Load Cell + HX711 | C14: 12 | D14: 13 | E14: =C14*D14
A15: 12 | B15: Smart Milk Meter | C15: 12 | D15: 51 | E15: =C15*D15
... A27: 24 | B27: Wires & Installation | C27: 1 | D27: 39 | E27: =C27*D27
A28: TOTAL HARDWARE COST | E28: =SUM(E4:E27)

Sheet Budget Summary
A1: MooMe — 3-Year Budget Summary
A3: Category | B3: Year 1 (USD) | C3: Year 2 (USD) | D3: Year 3 (USD) | E3: Total (USD) | F3: % of Total
A4: Solution Design | B4: ='Quarterly Budget Logframe'!G12 | C4: ='Quarterly Budget Logframe'!L12 | D4: ='Quarterly Budget Logframe'!Q12 | E4: ='Quarterly Budget Logframe'!R12 | F4: =IF(E$7=0,"",E4/E$7)
A5: Solution Development | B5: ='Quarterly Budget Logframe'!G20 | C5: ='Quarterly Budget Logframe'!L20 | D5: ='Quarterly Budget Logframe'!Q20 | E5: ='Quarterly Budget Logframe'!R20 | F5: =IF(E$7=0,"",E5/E$7)
A6: Solution Promotion | B6: ='Quarterly Budget Logframe'!G27 | C6: ='Quarterly Budget Logframe'!L27 | D6: ='Quarterly Budget Logframe'!Q27 | E6: ='Quarterly Budget Logframe'!R27 | F6: =IF(E$7=0,"",E6/E$7)
A7: GRAND TOTAL | B7: =SUM(B4:B6) | C7: =SUM(C4:C6) | D7: =SUM(D4:D6) | E7: =SUM(E4:E6) | F7: =SUM(F4:F6)
